yapigo/__init__.py
yapigo/utils.py
yapigo-1.0.1.dist-info/LICENSE
yapigo-1.0.1.dist-info/METADATA
yapigo-1.0.1.dist-info/WHEEL
yapigo-1.0.1.dist-info/top_level.txt
yapigo-1.0.1.dist-info/RECORD
