Metadata-Version: 2.1
Name: yapigo
Version: 1.0.1
Summary: Yapigo Utility Package
Author-email: Vincent Cantin Bellemare <cantinbellemare@gmail.com>
Project-URL: Homepage, https://github.com/pypa/yapigo
Project-URL: Bug Tracker, https://github.com/pypa/sampleproject/issues
Classifier: Programming Language :: Python :: 3
Classifier: License :: OSI Approved :: MIT License
Classifier: Operating System :: OS Independent
Requires-Python: >=3.7
License-File: LICENSE
